{
  "name": "customer_status",
  "description": "This function is to search for the customer's account status based on the customer's ID or name.\n-Input ID and customer name\n-Output customer's account status\n-nationality",
  "color": "linear-gradient(rgb(1,103,139), rgb(108,217,174))",
  "iconSrc": "",
  "schema": "[{\"id\":0,\"property\":\"custID\",\"description\":\"custID\",\"type\":\"string\",\"required\":true},{\"id\":1,\"property\":\"custname\",\"description\":\"customername\",\"type\":\"string\",\"required\":true}]",
  "func": "try {\n\n  const customers = {\n    \"1111\": { \n      name: \"loren\", \n      nationality: \"Singaporean\", \n      email: \"loren@gmail.com\", \n      status: \"good-standing\"\n    },\n    \"2222\": { \n      name: \"matt\", \n      nationality: \"Non-Singaporean\", \n      email: \"matt@yahoo.com\", \n      status: \"Closed\"\n    },\n    \"3333\": { \n      name: \"hilda\", \n      nationality: \"Singaporean\", \n      email: \"hilda@gmail.com\", \n      status: \"delinquent\"\n    },\n    \"4444\": { \n      name: \"andy\", \n      nationality: \"Non-Singaporean\", \n      email: \"andy@gmail.com\", \n      status: \"good-standing\"\n    },\n    \"5555\": { \n      name: \"kit\", \n      nationality: \"Singaporean\", \n      email: \"kit@yahoo.com\", \n      status: \"delinquent\"\n    }\n  };\n\n  custID = $custID.toString();\n  custname = $custname.toLowerCase();\n\n  const record = customers[custID];\n\n  // ID not found\n  if (!record) {\n    return { \n      account_status: null,\n      nationality: null\n    };\n  }\n\n  // Match name\n  if (record.name === custname) {\n    return { \n      account_status: record.status,\n      nationality: record.nationality\n    };\n  }\n\n  // Name does not match\n  return { \n    account_status: null,\n    nationality: null\n  };\n\n} catch (error) {\n  return { \n    account_status: null,\n    nationality: null,\n    error: error.message \n  };\n}",
  "workspaceId": "140a27b8-cb2d-4b39-92d0-d3f3b0128c94"
}